<?xml version="1.0" encoding="UTF-8"?>
<!DOCTYPE mapper PUBLIC "-//mybatis.org//DTD Mapper 3.0//EN" "http://mybatis.org/dtd/mybatis-3-mapper.dtd"> 
<mapper namespace="com.hotent.platform.model.system.SysTemplate">
	<resultMap id="SysTemplate" type="com.hotent.platform.model.system.SysTemplate">
		<id property="templateId" column="templateId" jdbcType="NUMERIC"/>
		<result property="templateType" column="templateType" jdbcType="NUMERIC"/>
		<result property="name" column="name" jdbcType="VARCHAR"/>
		<result property="content" column="content" jdbcType="CLOB"/>
		<result property="isDefault" column="isDefault" jdbcType="NUMERIC"/>
		<result property="isSystemTemp" column="isSystemTemp" jdbcType="NUMERIC"/>
	</resultMap>
	
	<sql id="columns">
		templateId,templateType,name,content,isDefault,isSystemTemp
	</sql>
	
	<sql id="dynamicWhere">
		<where>
			<if test="@Ognl@isNotEmpty(templateId)"> AND templateId  =#{templateId} </if>
			<if test="@Ognl@isNotEmpty(templateType)"> AND templateType  =#{templateType} </if>
			<if test="@Ognl@isNotEmpty(name)"> AND name  LIKE #{name}  </if>
			<if test="@Ognl@isNotEmpty(content)"> AND content  LIKE #{content}  </if>
		</where>
	</sql>

	<insert id="add" parameterType="com.hotent.platform.model.system.SysTemplate">
		INSERT INTO sys_template
		(<include refid="columns"/>)
		VALUES
		(#{templateId,jdbcType=NUMERIC}, #{templateType,jdbcType=NUMERIC}, #{name,jdbcType=VARCHAR}, #{content,jdbcType=CLOB}, #{isDefault,jdbcType=NUMERIC}, #{isSystemTemp,jdbcType=NUMERIC})
	</insert>
	
	<delete id="delById" parameterType="java.lang.Long">
		DELETE FROM SYS_TEMPLATE 
		WHERE
		templateId=#{templateId}
	</delete>
	
	<update id="update" parameterType="com.hotent.platform.model.system.SysTemplate">
		UPDATE sys_template SET
		templateType=#{templateType,jdbcType=NUMERIC} , 
		name=#{name,jdbcType=VARCHAR} , 
		content=#{content,jdbcType=CLOB},
		isDefault=#{isDefault,jdbcType=NUMERIC} ,
		isSystemTemp=#{isSystemTemp,jdbcType=NUMERIC}
		WHERE
		templateId=#{templateId}
	</update>
	
	<select id="getById" parameterType="java.lang.Long" resultMap="SysTemplate">
		SELECT <include refid="columns"/>
		FROM SYS_TEMPLATE
		WHERE
		templateId=#{templateId}
	</select>
	
	<select id="getAll" resultMap="SysTemplate">
		SELECT <include refid="columns"/>
		FROM SYS_TEMPLATE   
		<include refid="dynamicWhere" />
		<if test="@Ognl@isNotEmpty(orderField)">
		order by ${orderField} ${orderSeq}
		</if>
		<if test="@Ognl@isEmpty(orderField)">
		order by templateId  desc
		</if>
	</select>
	
	<update id="updateNotDefaultByTempType" parameterType="java.lang.Integer">
		UPDATE SYS_TEMPLATE SET isDefault=0 where templatetype=#{tempType}
	</update>
	
	<update id="updateDefault" parameterType="java.lang.Long">
		UPDATE SYS_TEMPLATE SET
		isDefault=1 WHERE templateId=#{id}
	</update>
	
	<select id="getDefaultByType"  resultMap="SysTemplate" parameterType="java.lang.Integer">
		SELECT <include refid="columns"/>
		FROM SYS_TEMPLATE
		WHERE isDefault=1
		and templatetype=#{tempType}
	</select>
	
	<select id="getSystemByType" resultMap="SysTemplate" parameterType="java.lang.Integer">
		SELECT <include refid="columns"/>
		FROM SYS_TEMPLATE
		WHERE issystemtemp=1
		and templatetype=#{tempType}
	</select>
</mapper>
